restmapper/__init__.py
restmapper/exceptions.py
restmapper/metadata.py
restmapper/restmapper.py
restmapper-2.0.1.dist-info/DESCRIPTION.rst
restmapper-2.0.1.dist-info/METADATA
restmapper-2.0.1.dist-info/RECORD
restmapper-2.0.1.dist-info/WHEEL
restmapper-2.0.1.dist-info/metadata.json
restmapper-2.0.1.dist-info/top_level.txt
