Metadata-Version: 2.0
Name: restmapper
Version: 2.0.1
Summary: RestMapper takes the pain out of integrating with RESTful APIs
Home-page: https://github.com/lionheart/python-restmapper
Author: Dan Loewenherz
Author-email: dan@lionheartsw.com
License: Apache 2.0
Keywords: restmapper
Platform: UNKNOWN
Classifier: Development Status :: 5 - Production/Stable
Classifier: Environment :: Console
Classifier: Intended Audience :: Developers
Classifier: Natural Language :: English
Classifier: Operating System :: OS Independent
Classifier: Programming Language :: Python
Classifier: Topic :: Software Development :: Libraries :: Python Modules
Classifier: Topic :: Internet :: WWW/HTTP :: Dynamic Content :: CGI Tools/Libraries
Classifier: Topic :: Utilities
Classifier: License :: OSI Approved :: Apache Software License
Requires-Dist: requests (>=2.0.0)
